mrapids/__init__.py
mrapids/mrapids.cpython-39-x86_64-linux-gnu.so
mrapids-0.1.7.dist-info/METADATA
mrapids-0.1.7.dist-info/WHEEL
mrapids-0.1.7.dist-info/RECORD
