Metadata-Version: 2.4
Name: mrapids
Version: 0.1.7
Classifier: Programming Language :: Rust
Classifier: Programming Language :: Python :: Implementation :: CPython
Classifier: Programming Language :: Python :: Implementation :: PyPy
Classifier: Development Status :: 4 - Beta
Classifier: Intended Audience :: Developers
Classifier: License :: OSI Approved :: MIT License
Classifier: Operating System :: OS Independent
Classifier: Topic :: Software Development :: Libraries :: Python Modules
Classifier: Topic :: Internet :: WWW/HTTP :: Dynamic Content
Summary: Python bindings for MicroRapids API Runtime - high-performance API client built with Rust
Keywords: api,client,rust,performance,openapi
Author-email: MicroRapids Team <info@microrapids.com>
License: MIT
Requires-Python: >=3.8
Project-URL: homepage, https://github.com/microrapids/api-runtime
Project-URL: repository, https://github.com/microrapids/api-runtime
